adder.v
module adder(
    input  [3:0]a, [3:0]b, 
    output reg [3:0] r,
    output co
)
assign {co, r} <= a + b

endmodule

io.v
module io(
    input clk,rst,load,
    input [3:0] di,
    output reg [9:0] LEDR
);

always @(posedge clk) begin
    if(rst)
        LEDR = 4'b0000;
    else if(!load)
        LEDR = di;
end

endmodule

register.v
module register(
    input clk,rst,load,
    input [3:0] d,
    output reg[3:0] qd
);

always @(posedge clk) begin
    if(rst)
        qd <= 4'b0;
    else if(!load)
        qd <= d;
end

endmodule

data_selecter.v
module data_selector(
    input [3:0] a,b,out,
    input [1:0] select,
    output reg [3:0] qd
);

always @* begin
    case (select)
        2'b00 : qd <= a;
        2'b01 : qd <= b;
        2'b10 : qd <= out;
        2'b11 : qd <= 4'b0000;
    endcase
end

endmodule

decoder.v
module decoder(
    input [3:0] data_input,
    input cflg,
    output reg [1:0] select,
    output reg [3:0] load
);

always @* begin
    case (data_input)
        4'b0000 : begin select <= 2'b00; load <= 4'b1110; end 
        4'b0001 : begin select <= 2'b01; load <= 4'b1110; end 
        4'b0010 : begin select <= 2'b10; load <= 4'b1110; end 
        4'b0011 : begin select <= 2'b11; load <= 4'b1110; end
        4'b0100 : begin select <= 2'b00; load <= 4'b1101; end
        4'b0101 : begin select <= 2'b01; load <= 4'b1101; end
        4'b0110 : begin select <= 2'b10; load <= 4'b1101; end
        4'b0111 : begin select <= 2'b11; load <= 4'b1101; end
        4'b1001 : begin select <= 2'b01; load <= 4'b1011; end
        4'b1011 : begin select <= 2'b11; load <= 4'b1011; end
        4'b1110 : begin 
            if(cflg) begin select <= 2'b00; load <= 4'b1111; end
            else     begin select <= 2'b11; load <= 4'b0111; end
        end
        4'b1111 : begin select <= 2'b11; load <= 4'b0111; end
    endcase
end

endmodule

cnt.v
module counter(
    input clk,rst,load
    input [3:0] di,
    output reg [3:0] qd
);

always @(posedge clk) begin
    if(rst | di == 4'b1111)
        qd <= 4'b0000;
    else if(!load)
        qd <= di;
    else 
        qd <= qd + 1;
end

endmodule

rom.v
module rom(
    input clk, rst,
    input [3:0] addr,
    output reg[7:0] qd
);

always @* begin
    case(addr)
        4'b0000: qd <= 8'b10110011;
        4'b0001: qd <= 8'b10110110;
        4'b0010: qd <= 8'b10111100;
        4'b0011: qd <= 8'b10111000;
        4'b0100: qd <= 8'b10111000;
        4'b0101: qd <= 8'b10111100;
        4'b0110: qd <= 8'b10110110;
        4'b0111: qd <= 8'b10110011;
        4'b1000: qd <= 8'b10110001;
        4'b1001: qd <= 8'b11110000;
    endcase
end

endmodule

cpu_sim.v
module cpu(
    input CLK, RST,
    output [9:0] LEDR
);

wire [3:0] addr;
wire [7:0] data_bus;
wire cflg;
wire [1:0] select;
wire [3:0] load;
wire [3:0] a;
wire [3:0] b;
wire [3:0] out;
wire [3:0] selector_out;
wire [3:0] adder_out;


rom rom(
    .clk(CLK), 
    .rst(RST), 
    .addr(addr),
    .qd(data_bus)
);

counter counter(
    .clk(CLK),
    .rst(RST),
    .load(load[3]),
    .di(adder_out),
    .qd(addr)
);

decoder decoder(
    .data_input(data_bus[7:4]),
    .cflg(cflg),
    .select(select),
    .load(load)
);

data_selector data_selector(
    .a(a),
    .b(b),
    .select(select),
    .out(out),
    .qd(selector_out)
 );

register a_reg(
    .clk(CLK),
    .rst(RST),
    .load(load[0]),
    .d(adder_out),
    .qd(a)
);

register b_reg(
    .clk(CLK),
    .rst(RST),
    .load(load[1]),
    .d(adder_out),
    .qd(b)
);

io out_put(
    .clk(CLK),
    .rst(RST),
    .di(adder_out),
    .load(load[2]),
    .LEDR(LEDR)
);

adder adder(
    .a(selector_out),
    .b(data_bus[3:0]),
    .r(adder_out),
    .co(cflg)
);

endmodule

cpu_tb.v

`timescale 1ns / 1ps

module test;
    reg reset = 0;
    reg clk = 0;
    wire [9:0] led;

    cpu a(clk, reset, led);
    
    initial begin
        clk = 0;    
    end

    always #5 clk = !clk;

    initial begin 
        reset = 0;
        repeat(2) @(posedge clk) reset <= 1;
        @(posedge clk) reset <= 0;
    end

    initial begin
        #150 
        $finish;
    end


    initial begin
        $monitor("led=%b", led);
        $dumpfile("cpu_tb.vcd");
        $dumpvars(0, a);
    end

 endmodule

cpu_tb.vcd
$date
	Sat Jul 10 16:25:58 2021
$end
$version
	Icarus Verilog
$end
$timescale
	1ps
$end
$scope module test $end
$scope module a $end
$var wire 1 ! CLK $end
$var wire 1 " RST $end
$var wire 4 # out [3:0] $end
$var wire 4 $ selector_out [3:0] $end
$var wire 2 % select [1:0] $end
$var wire 4 & load [3:0] $end
$var wire 8 ' data_bus [7:0] $end
$var wire 1 ( cflg $end
$var wire 4 ) b [3:0] $end
$var wire 4 * addr [3:0] $end
$var wire 4 + adder_out [3:0] $end
$var wire 4 , a [3:0] $end
$var wire 10 - LEDR [9:0] $end
$scope module a_reg $end
$var wire 1 ! clk $end
$var wire 1 . load $end
$var wire 1 " rst $end
$var wire 4 / d [3:0] $end
$var reg 4 0 qd [3:0] $end
$upscope $end
$scope module adder $end
$var wire 4 1 b [3:0] $end
$var wire 4 2 r [3:0] $end
$var wire 1 ( co $end
$var wire 4 3 a [3:0] $end
$upscope $end
$scope module b_reg $end
$var wire 1 ! clk $end
$var wire 4 4 d [3:0] $end
$var wire 1 5 load $end
$var wire 1 " rst $end
$var reg 4 6 qd [3:0] $end
$upscope $end
$scope module counter $end
$var wire 1 ! clk $end
$var wire 4 7 di [3:0] $end
$var wire 1 8 load $end
$var wire 1 " rst $end
$var reg 4 9 qd [3:0] $end
$upscope $end
$scope module data_selector $end
$var wire 4 : a [3:0] $end
$var wire 4 ; b [3:0] $end
$var wire 4 < out [3:0] $end
$var wire 2 = select [1:0] $end
$var reg 4 > qd [3:0] $end
$upscope $end
$scope module decoder $end
$var wire 1 ( cflg $end
$var wire 4 ? data_input [3:0] $end
$var reg 4 @ load [3:0] $end
$var reg 2 A select [1:0] $end
$upscope $end
$scope module out_put $end
$var wire 1 ! clk $end
$var wire 4 B di [3:0] $end
$var wire 1 C load $end
$var wire 1 " rst $end
$var reg 10 D LEDR [9:0] $end
$upscope $end
$scope module rom $end
$var wire 4 E addr [3:0] $end
$var wire 1 ! clk $end
$var wire 1 " rst $end
$var reg 8 F qd [7:0] $end
$upscope $end
$upscope $end
$upscope $end
$enddefinitions $end
#0
$dumpvars
bx F
bx E
bx D
xC
bx B
bx A
bx @
bx ?
bx >
bx =
bz <
bx ;
bx :
bx 9
x8
bx 7
bx 6
x5
bx 4
bx 3
bx 2
bx 1
bx 0
bx /
x.
bx -
bx ,
bx +
bx *
bx )
x(
bx '
bx &
bx %
bx $
bz #
0"
0!
$end
#5000
1"
1!
#10000
0!
#15000
b11 +
b11 /
b11 2
b11 4
b11 7
b11 B
0(
b0 $
b0 3
b0 >
0C
15
1.
18
b1011 &
b1011 @
b11 %
b11 =
b11 A
b11 1
b1011 ?
b10110011 '
b10110011 F
b0 )
b0 6
b0 ;
b0 ,
b0 0
b0 :
b0 *
b0 9
b0 E
b0 -
b0 D
1!
#20000
0!
#25000
0"
1!
#30000
0!
#35000
b110 +
b110 /
b110 2
b110 4
b110 7
b110 B
b110 1
b10110110 '
b10110110 F
b1 *
b1 9
b1 E
b11 -
b11 D
1!
#40000
0!
#45000
b1100 +
b1100 /
b1100 2
b1100 4
b1100 7
b1100 B
b1100 1
b10111100 '
b10111100 F
b10 *
b10 9
b10 E
b110 -
b110 D
1!
#50000
0!
#55000
b1000 +
b1000 /
b1000 2
b1000 4
b1000 7
b1000 B
b1000 1
b10111000 '
b10111000 F
b11 *
b11 9
b11 E
b1100 -
b1100 D
1!
#60000
0!
#65000
b100 *
b100 9
b100 E
b1000 -
b1000 D
1!
#70000
0!
#75000
b1100 +
b1100 /
b1100 2
b1100 4
b1100 7
b1100 B
b1100 1
b10111100 '
b10111100 F
b101 *
b101 9
b101 E
1!
#80000
0!
#85000
b110 +
b110 /
b110 2
b110 4
b110 7
b110 B
b110 1
b10110110 '
b10110110 F
b110 *
b110 9
b110 E
b1100 -
b1100 D
1!
#90000
0!
#95000
b11 +
b11 /
b11 2
b11 4
b11 7
b11 B
b11 1
b10110011 '
b10110011 F
b111 *
b111 9
b111 E
b110 -
b110 D
1!
#100000
0!
#105000
b1 +
b1 /
b1 2
b1 4
b1 7
b1 B
b1 1
b10110001 '
b10110001 F
b1000 *
b1000 9
b1000 E
b11 -
b11 D
1!
#110000
0!
#115000
1C
08
b111 &
b111 @
b0 +
b0 /
b0 2
b0 4
b0 7
b0 B
b0 1
b1111 ?
b11110000 '
b11110000 F
b1001 *
b1001 9
b1001 E
b1 -
b1 D
1!
#120000
0!
#125000
0C
18
b1011 &
b1011 @
b11 +
b11 /
b11 2
b11 4
b11 7
b11 B
b11 1
b1011 ?
b10110011 '
b10110011 F
b0 *
b0 9
b0 E
1!
#130000
0!
#135000
b110 +
b110 /
b110 2
b110 4
b110 7
b110 B
b110 1
b10110110 '
b10110110 F
b1 *
b1 9
b1 E
b11 -
b11 D
1!
#140000
0!
#145000
b1100 +
b1100 /
b1100 2
b1100 4
b1100 7
b1100 B
b1100 1
b10111100 '
b10111100 F
b10 *
b10 9
b10 E
b110 -
b110 D
1!
